odoo/addons/res_company_category/README.rst
odoo/addons/res_company_category/__init__.py
odoo/addons/res_company_category/__manifest__.py
odoo/addons/res_company_category/demo/res_company.xml
odoo/addons/res_company_category/demo/res_company_category.xml
odoo/addons/res_company_category/demo/res_groups.xml
odoo/addons/res_company_category/i18n/fr.po
odoo/addons/res_company_category/i18n/res_company_category.pot
odoo/addons/res_company_category/models/__init__.py
odoo/addons/res_company_category/models/res_company.py
odoo/addons/res_company_category/models/res_company_category.py
odoo/addons/res_company_category/readme/CONFIGURE.rst
odoo/addons/res_company_category/readme/CONTRIBUTORS.rst
odoo/addons/res_company_category/readme/DESCRIPTION.rst
odoo/addons/res_company_category/security/ir.model.access.csv
odoo/addons/res_company_category/static/description/icon.png
odoo/addons/res_company_category/static/description/index.html
odoo/addons/res_company_category/static/description/res_company_category_form.png
odoo/addons/res_company_category/static/description/res_company_category_tree.png
odoo/addons/res_company_category/static/description/res_company_form.png
odoo/addons/res_company_category/views/view_res_company.xml
odoo/addons/res_company_category/views/view_res_company_category.xml
odoo12_addon_res_company_category-12.0.1.0.0.99.dev6.dist-info/METADATA
odoo12_addon_res_company_category-12.0.1.0.0.99.dev6.dist-info/WHEEL
odoo12_addon_res_company_category-12.0.1.0.0.99.dev6.dist-info/top_level.txt
odoo12_addon_res_company_category-12.0.1.0.0.99.dev6.dist-info/RECORD
